Workbook

Sheet Assumptions Dashboard
B2: PROJECT ASSUMPTIONS
B4: Project Name: Queens Multifamily Development
B5: Location: Long Island City, Queens NY
B6: Analysis Start: 12/31/2025
B9: UNIT MIX
B10: Unit Type | C10: Unit | D10: SF/Unit | E10: Monthly Rent | F10: Annual Rent/ Unit | G10: Total Annual Revenue
C11: 10 | D11: 450 | E11: 2200 | F11: =E11*12 -> 26400 | G11: =C11*F11 -> 264000
B12: 1 Bedroom | C12: 25 | D12: 650 | E12: 2800 | F12: =E12*12 -> 33600 | G12: =C12*F12 -> 840000
B13: 2 Bedroom | C13: 15 | D13: 900 | E13: 3800 | F13: =E13*12 -> 45600 | G13: =C13*F13 -> 684000
B14: Total/Avg | C14: =SUM(C11:C13) -> 50 | F14: =SUMPRODUCT(C11:C13,F11:F13)/C14 -> 35760 | G14: =C14*F14 -> 1788000
B17: BUILDING SIZE
B18: Total NRSF | C18: =SUMPRODUCT(C11:C13,D11:D13) -> 34250
B19: Efficency | C19: 0.85
B20: Total GSF | C20: =C18/C19 -> 40294.118
B23: DEVELOPMENT COSTS
B24: Land Cost/GSF | C24: 150
B25: Hard Cost/GSF | C25: 350
B26: Soft Cost/GSF | C26: 75
B27: Total Land Cost | C27: =C24*C20 -> 6044117.6
B28: Total Hard Cost | C28: =C25*C20 -> 14102941
B29: Total Soft Cost | C29: =C26*C20 -> 3022058.8
B30: Total Development Cost | C30: =SUM(C27:C29) -> 23169118
B33: Operating Assumption
B34: Vacancy Rate | C34: 0.05
B35: OpEx/Unit/Year | C35: 8500
B36: RE Taxes/Unit/Year | C36: 4000
B37: Rent Escalation | C37: 0.025
B38: Expense Escalation | C38: 0.025
B41: Financing
B42: Loan to Cost | C42: 0.65
B43: Intrest Rate | C43: 0.07
B44: Loan Ammount | C44: =C30*C42 -> 15059926
B45: Equity Required | C45: =C30-C44 -> 8109191.2
B47: Exit Assumptions
B48: Hold Periods | C48: 5
B49: Exit Cap Rate | C49: 0.0475
B50: Sales Costs | C50: 0.02

Sheet Development Budget
B2: Development & Budget | C2: Total | D2: 2026 | E2: 2027 | F2: 2028
B3: Land | C3: ='Assumptions Dashboard'!C20*'Assumptions Dashboard'!C24 -> 6044117.6 | D3: =C3 -> 6044117.6
B4: Hard Cost | C4: ='Assumptions Dashboard'!C20*'Assumptions Dashboard'!C25 -> 14102941 | E4: =C4*1/3 -> 4700980.4 | F4: =C4*2/3 -> 9401960.8
B5: Soft Cost | C5: ='Assumptions Dashboard'!C20*'Assumptions Dashboard'!C26 -> 3022058.8 | D5: =C5 -> 3022058.8
B6: Total Cost | C6: =SUM(C3:C5) -> 23169118 | D6: =SUM(D3:D5) -> 9066176.5 | E6: =SUM(E3:E5) -> 4700980.4 | F6: =SUM(F3:F5) -> 9401960.8
B10: Sources & Uses
B11: USES
B12: Land | C12: =C3 -> 6044117.6
B13: Hard Cost | C13: =C4 -> 14102941
B14: Soft Cost | C14: =C5 -> 3022058.8
B15: Total Uses | C15: =SUM(C12:C14) -> 23169118
B16: SOURCES
B17: Construction Loan | C17: ='Assumptions Dashboard'!C44 -> 15059926
B18: Equity | C18: ='Assumptions Dashboard'!C45 -> 8109191.2
B19: Total Sources | C19: =SUM(C17:C18) -> 23169118
B20: Variance | C20: =C15-C19 -> 0
B22: Construction Loan Draw Schedule | C22: Total | D22: 2026 | E22: 2027 | F22: 2028
B23: Total Cost | C23: =C6 -> 23169118 | D23: =D6 -> 9066176.5 | E23: =E6 -> 4700980.4 | F23: =F6 -> 9401960.8
B24: Loan Draw (65%) | C24: =C23*'Assumptions Dashboard'!C42 -> 15059926 | D24: =D23*'Assumptions Dashboard'!C42 -> 5893014.7 | E24: =E23*'Assumptions Dashboard'!C42 -> 3055637.3 | F24: =F23*'Assumptions Dashboard'!C42 -> 6111274.5
B25: Cumulative Loan Balance | D25: =D24 -> 5893014.7 | E25: =D25+E24 -> 8948652 | F25: =E25+F24 -> 15059926
B28: Equity Contribution Schedule | C28: Total | D28: 2026 | E28: 2027 | F28: 2028
B29: Total Cost | C29: =C23 -> 23169118 | D29: =D23 -> 9066176.5 | E29: =E23 -> 4700980.4 | F29: =F23 -> 9401960.8
B30: Equity Draw (35%) | C30: =C29*0.35 -> 8109191.2 | D30: =D29*0.35 -> 3173161.8 | E30: =E29*0.35 -> 1645343.1 | F30: =F29*0.35 -> 3290686.3
B31: Cumulative Equity Draw | D31: =D30 -> 3173161.8 | E31: =D31+E30 -> 4818504.9 | F31: =E31+F30 -> 8109191.2
B33: Key Metric Summary
B34: Total Development Cost | C34: =C6 -> 23169118
B35: Cost Per Unit | C35: =C34/50 -> 463382.35
B36: Cost Per GSF | C36: =C34/'Assumptions Dashboard'!C20 -> 575
B37: Land as % of Total Cost | C37: =C12/C6 -> 0.26086957
B38: Hard Cost as % of Total Cost | C38: =C13/C6 -> 0.60869565
B39: Soft Cost as % of Total Cost | C39: =C14/C6 -> 0.13043478

Sheet Pro Forma
A2: Operating Pro Forma | B2: 2029 | C2: 2030 | D2: 2031 | E2: 2032 | F2: 2033
A3: Gross Potential Rent | B3: ='Assumptions Dashboard'!G14*(1.025)^3 -> 1925480.4 | C3: =B3*(1+'Assumptions Dashboard'!C37) -> 1973617.4 | D3: =C3*(1+'Assumptions Dashboard'!C37) -> 2022957.9 | E3: =D3*(1+'Assumptions Dashboard'!C37) -> 2073531.8 | F3: =E3*(1+'Assumptions Dashboard'!C37) -> 2125370.1
A4: Vacancy Loss | B4: =B3*'Assumptions Dashboard'!C34 -> 96274.022 | C4: =C3*'Assumptions Dashboard'!C34 -> 98680.872 | D4: =D3*'Assumptions Dashboard'!C34 -> 101147.89 | E4: =E3*'Assumptions Dashboard'!C34 -> 103676.59 | F4: =F3*'Assumptions Dashboard'!C34 -> 106268.51
A5: Effective Gross Income | B5: =B3-B4 -> 1829206.4 | C5: =C3-C4 -> 1874936.6 | D5: =D3-D4 -> 1921810 | E5: =E3-E4 -> 1969855.2 | F5: =F3-F4 -> 2019101.6
A9: Operating Expenses | B9: 2029 | C9: 2030 | D9: 2031 | E9: 2032 | F9: 2033
A10: OpEx | B10: =('Assumptions Dashboard'!$C$35*'Assumptions Dashboard'!$C$14)*(1+'Assumptions Dashboard'!$C$38)^3 -> 457678.52 | C10: =B10*(1.025) -> 469120.48 | D10: =C10*(1.025) -> 480848.49 | E10: =D10*(1.025) -> 492869.7 | F10: =E10*(1.025) -> 505191.45
A11: RE Tax | B11: =('Assumptions Dashboard'!C36*'Assumptions Dashboard'!C14)*(1.025)^3 -> 215378.12 | C11: =B11*(1.025) -> 220762.58 | D11: =C11*(1.025) -> 226281.64 | E11: =D11*(1.025) -> 231938.68 | F11: =E11*(1.025) -> 237737.15
A12: Total Expense | B12: =SUM(B10:B11) -> 673056.64 | C12: =SUM(C10:C11) -> 689883.06 | D12: =SUM(D10:D11) -> 707130.13 | E12: =SUM(E10:E11) -> 724808.39 | F12: =SUM(F10:F11) -> 742928.6
A16: Net Operating Income | B16: 2029 | C16: 2030 | D16: 2031 | E16: 2032 | F16: 2033
A17: NOI | B17: =B5-B12 -> 1156149.8 | C17: =C5-C12 -> 1185053.5 | D17: =D5-D12 -> 1214679.9 | E17: =E5-E12 -> 1245046.9 | F17: =F5-F12 -> 1276173
A21: Cash Flow | B21: 2029 | C21: 2030 | D21: 2031 | E21: 2032 | F21: 2033
A22: NOI | B22: =B17 -> 1156149.8 | C22: =C17 -> 1185053.5 | D22: =D17 -> 1214679.9 | E22: =E17 -> 1245046.9 | F22: =F17 -> 1276173
A23: Dept Service | B23: ='Debt Schedule '!B19 -> 1168453.2 | C23: ='Debt Schedule '!C19 -> 1168453.2 | D23: ='Debt Schedule '!D19 -> 1168453.2 | E23: ='Debt Schedule '!E19 -> 1168453.2 | F23: ='Debt Schedule '!F21 -> 17860642
A24: Cash Flow to Equity | B24: =B22-B23 -> -12303.46 | C24: =C22-C23 -> 16600.284 | D24: =D22-D23 -> 46226.622 | E24: =E22-E23 -> 76593.619 | F24: =F22-F23 -> -16584469

Sheet Debt Schedule 
A2: Debt Schedule | B2: 2026 | C2: 2027 | D2: 2028
A3: Beggining Balance | C3: =B6 -> 6099270.2 | D3: =C6 -> 9688803.7
A4: Loan Draw | B4: ='Development Budget'!D24 -> 5893014.7 | C4: ='Development Budget'!E24 -> 3055637.3 | D4: ='Development Budget'!F24 -> 6111274.5
A5: Interest (7%) | B5: =B4*'Assumptions Dashboard'!C43/2 -> 206255.51 | C5: =(C3*'Assumptions Dashboard'!C43)+('Debt Schedule '!C4*'Assumptions Dashboard'!C43/2) -> 533896.22 | D5: =(D3*'Assumptions Dashboard'!C43)+('Debt Schedule '!D4*'Assumptions Dashboard'!C43/2) -> 892110.87
A6: Ending Balance | B6: =SUM(B4:B5) -> 6099270.2 | C6: =SUM(C3:C5) -> 9688803.7 | D6: =SUM(D3:D5) -> 16692189
A10: Operating Period | B10: 2029 | C10: 2030 | D10: 2031 | E10: 2032 | F10: 2033
A11: Beggining Balance | B11: =D6 -> 16692189 | C11: =D6 -> 16692189 | D11: =D6 -> 16692189 | E11: =D6 -> 16692189 | F11: =D6 -> 16692189
A12: Interest Payment | B12: =B11*'Assumptions Dashboard'!$C$43 -> 1168453.2 | C12: =C11*'Assumptions Dashboard'!$C$43 -> 1168453.2 | D12: =D11*'Assumptions Dashboard'!$C$43 -> 1168453.2 | E12: =E11*'Assumptions Dashboard'!$C$43 -> 1168453.2 | F12: =F11*'Assumptions Dashboard'!$C$43 -> 1168453.2
A13: Principal Payment | F13: =E11 -> 16692189
A14: Ending Balance | B14: =B11-B13 -> 16692189 | C14: =C11-C13 -> 16692189 | D14: =D11-D13 -> 16692189 | E14: =E11-E13 -> 16692189 | F14: =F11-F13 -> 0
A18: Debt Service Summary | B18: =B10 -> 2029 | C18: =C10 -> 2030 | D18: =D10 -> 2031 | E18: =E10 -> 2032 | F18: =F10 -> 2033
A19: =A12 -> Interest Payment | B19: =B12 -> 1168453.2 | C19: =C12 -> 1168453.2 | D19: =D12 -> 1168453.2 | E19: =E12 -> 1168453.2 | F19: =F12 -> 1168453.2
A20: Payment Principal | F20: =F13 -> 16692189
A21: Total Debt Service | F21: =F19+F20 -> 17860642

Sheet  Returns
B2: Exit Calculations
B3: 2033 NOI | C3: ='Pro Forma'!F17 -> 1276173
B4: Exit Cap Rate | C4: ='Assumptions Dashboard'!C49 -> 0.0475
B5: Sales Price | C5: =C3/C4 -> 26866801
B6: Sales Cost % | C6: ='Assumptions Dashboard'!C50 -> 0.02
B7: Net Sales Proceeds | C7: =C5*(1-C6) -> 26329465
B8: Loan Payoff | C8: ='Debt Schedule '!F13 -> 16692189
B9: Net Proceeds to Equity | C9: =C7-C8 -> 9637275.4
B13: Unlevered Cash Flow | C13: 2026 | D13: 2027 | E13: 2028 | F13: 2029 | G13: 2030 | H13: 2031 | I13: 2032 | J13: 2033
B14: Total Cost | C14: =-'Development Budget'!D6 -> -9066176.5 | D14: =-'Development Budget'!E6 -> -4700980.4 | E14: =-'Development Budget'!F6 -> -9401960.8
B15: NOI | F15: ='Pro Forma'!B17 -> 1156149.8 | G15: ='Pro Forma'!C17 -> 1185053.5 | H15: ='Pro Forma'!D17 -> 1214679.9 | I15: ='Pro Forma'!E17 -> 1245046.9 | J15: ='Pro Forma'!F17 -> 1276173
B16: Sales Proceeds | J16: =C7 -> 26329465
B17: Unlevered Cash Flow | C17: =SUM(C14:C16) -> -9066176.5 | D17: =SUM(D14:D16) -> -4700980.4 | E17: =SUM(E14:E16) -> -9401960.8 | F17: =SUM(F14:F16) -> 1156149.8 | G17: =SUM(G14:G16) -> 1185053.5 | H17: =SUM(H14:H16) -> 1214679.9 | I17: =SUM(I14:I16) -> 1245046.9 | J17: =SUM(J14:J16) -> 27605638
B22: Levered Cash Flow | C22: 2026 | D22: 2027 | E22: 2028 | F22: 2029 | G22: 2030 | H22: 2031 | I22: 2032 | J22: 2033
B23: Equity Contribution | C23: =-'Development Budget'!D30 -> -3173161.8 | D23: =-'Development Budget'!E30 -> -1645343.1 | E23: =-'Development Budget'!F30 -> -3290686.3
B24: Cash Flow To Equity | F24: ='Pro Forma'!B24 -> -12303.46 | G24: ='Pro Forma'!C24 -> 16600.284 | H24: ='Pro Forma'!D24 -> 46226.622 | I24: ='Pro Forma'!E24 -> 76593.619 | J24: ='Pro Forma'!F17 -> 1276173
B25: Net Proceeds to Equity | J25: =C9 -> 9637275.4
B26: Levered Cash Flow | C26: =SUM(C23:C25) -> -3173161.8 | D26: =SUM(D23:D25) -> -1645343.1 | E26: =SUM(E23:E25) -> -3290686.3 | F26: =SUM(F23:F25) -> -12303.46 | G26: =SUM(G23:G25) -> 16600.284 | H26: =SUM(H23:H25) -> 46226.622 | I26: =SUM(I23:I25) -> 76593.619 | J26: =SUM(J23:J25) -> 10913448
B29: Date | C29: 46387 | D29: 46752 | E29: 47118 | F29: 47483 | G29: 47848 | H29: 48213 | I29: 48579 | J29: 48944
B34: Summary Metrics
B35: Unlevered IRR | C35: =XIRR(C17:J17,C29:J29) -> 0.061550805
B36: Levered IRR | C36: =XIRR(C26:J26,C29:J29) -> 0.052824214
B37: Equity Multiple | C37: =SUM(F26:J26)/ABS(SUM(C26:E26)) -> 1.3614879
B38: Stabilized Yield on Cash | C38: =('Pro Forma'!B17/'Development Budget'!C19) -> 0.049900466
B39: Cash on Cash (avg) | C39: =AVERAGE(F26:I26)/ABS(SUM(C26:E26)) -> 0.0039189194

Sheet Sensitivity Tables
C1: Unlevered IRR vs Exit Cap Rate & Rents
B2: =' Returns'!C35 -> 0.061550805 | C2: 0.0425 | D2: 0.045 | E2: 0.0475 | F2: 0.05 | G2: 0.0525
B3: 10% Rents
B4: -5% Rent
B5: Base | E5: =' Returns'!C35 -> 0.061550805
B6: +5% Rent
B7: +10% Rent
